CHANGELOG.md
whitesmith-5.1.3.dist-info/METADATA
whitesmith-5.1.3.dist-info/WHEEL
whitesmith-5.1.3.dist-info/entry_points.txt
whitesmith-5.1.3.dist-info/licenses/LICENSE
whitesmith/__init__.py
whitesmith/domain/__index__.py
whitesmith/entrypoints/__init__.py
whitesmith/entrypoints/cli.py
whitesmith/entrypoints/plugin.py
whitesmith/generate_handlers.py
whitesmith/generate_openapis.py
whitesmith/model.py
whitesmith/py.typed
whitesmith/router.py
whitesmith/templates/handlers.jinja2
whitesmith/templates/redoc.jinja2
whitesmith/transport.py
whitesmith-5.1.3.dist-info/RECORD
