Metadata-Version: 2.1
Name: whitesmith
Version: 5.1.3
Summary: Testing toolbox for blacksmith
Author-Email: Guillaume Gauvrit <guillaume@gauvr.it>
License: MIT
Classifier: Development Status :: 5 - Production/Stable
Classifier: Intended Audience :: Developers
Classifier: License :: OSI Approved :: MIT License
Classifier: Topic :: Software Development :: Libraries :: Python Modules
Classifier: Topic :: Software Development :: Testing :: Mocking
Project-URL: Homepage, https://github.com/mardiros/whitesmith
Project-URL: Documentation, https://github.com/mardiros/whitesmith/blob/main/README.md
Project-URL: Repository, https://github.com/mardiros/whitesmith.git
Project-URL: Issues, https://github.com/mardiros/whitesmith/issues
Project-URL: Changelog, https://github.com/mardiros/whitesmith/blob/main/CHANGELOG.md
Requires-Python: >=3.10
Requires-Dist: Jinja2<4,>=3.1.2
Requires-Dist: blacksmith<6,>=5.0.1
Requires-Dist: polyfactory<3,>=2.14.0
Requires-Dist: pydantic<3,>=2.6.0
Requires-Dist: venusian<4,>=3.1.1
